{
    "poses": [
        {
            "handID": "R",
            "handPosition": {
                "x": 0.004486899357289076,
                "y": 0.4169461727142334,
                "z": -0.20024502277374268
            },
            "handRotation": {
                "x": 0.2878316044807434,
                "y": 0.7029834389686585,
                "z": -0.31526362895965578,
                "w": -0.568837583065033
            },
            "handOrientation": "Front",
            "fingerJoints": [
                {
                    "fingerName": "Thumb",
                    "jointPositions": [
                        {
                            "x": -0.022279713302850724,
                            "y": 0.4203733205795288,
                            "z": -0.18368829786777497
                        },
                        {
                            "x": -0.057566575706005099,
                            "y": 0.44068729877471926,
                            "z": -0.1588316559791565
                        },
                        {
                            "x": -0.07330667972564697,
                            "y": 0.45340609550476076,
                            "z": -0.14067356288433076
                        },
                        {
                            "x": -0.07929737865924835,
                            "y": 0.46376538276672366,
                            "z": -0.12241946905851364
                        }
                    ]
                },
                {
                    "fingerName": "Index",
                    "jointPositions": [
                        {
                            "x": -0.04036407917737961,
                            "y": 0.47509312629699709,
                            "z": -0.14395974576473237
                        },
                        {
                            "x": -0.0532960519194603,
                            "y": 0.49229925870895388,
                            "z": -0.12497676908969879
                        },
                        {
                            "x": -0.061554912477731708,
                            "y": 0.5016568899154663,
                            "z": -0.11031400412321091
                        },
                        {
                            "x": -0.06774910539388657,
                            "y": 0.5076591968536377,
                            "z": -0.09798115491867066
                        }
                    ]
                },
                {
                    "fingerName": "Middle",
                    "jointPositions": [
                        {
                            "x": -0.022557275369763376,
                            "y": 0.47984153032302859,
                            "z": -0.14225876331329347
                        },
                        {
                            "x": -0.029064172878861429,
                            "y": 0.5011255741119385,
                            "z": -0.11521877348423004
                        },
                        {
                            "x": -0.03379201889038086,
                            "y": 0.5127151608467102,
                            "z": -0.09389834105968476
                        },
                        {
                            "x": -0.037192534655332568,
                            "y": 0.5192265510559082,
                            "z": -0.07732488960027695
                        }
                    ]
                },
                {
                    "fingerName": "Ring",
                    "jointPositions": [
                        {
                            "x": -0.0013959496282041073,
                            "y": 0.4774512052536011,
                            "z": -0.14107513427734376
                        },
                        {
                            "x": -0.0031005011405795814,
                            "y": 0.49914634227752688,
                            "z": -0.11438191682100296
                        },
                        {
                            "x": -0.0051102470606565479,
                            "y": 0.5074064135551453,
                            "z": -0.09668635576963425
                        },
                        {
                            "x": -0.007431193720549345,
                            "y": 0.5126311182975769,
                            "z": -0.0798032134771347
                        }
                    ]
                },
                {
                    "fingerName": "Pinky",
                    "jointPositions": [
                        {
                            "x": 0.015367967076599598,
                            "y": 0.46937137842178347,
                            "z": -0.14138248562812806
                        },
                        {
                            "x": 0.017147626727819444,
                            "y": 0.48468196392059328,
                            "z": -0.1226939782500267
                        },
                        {
                            "x": 0.01625961810350418,
                            "y": 0.49138033390045168,
                            "z": -0.10502956807613373
                        },
                        {
                            "x": 0.014790114015340805,
                            "y": 0.4939196705818176,
                            "z": -0.09113232046365738
                        }
                    ]
                }
            ],
            "poseName": "base"
        },
        {
            "handID": "R",
            "handPosition": {
                "x": 0.01063630823045969,
                "y": 0.41412705183029177,
                "z": -0.204928457736969
            },
            "handRotation": {
                "x": 0.5899752974510193,
                "y": 0.7283918857574463,
                "z": 0.04832139611244202,
                "w": -0.34502124786376955
            },
            "handOrientation": "Front",
            "fingerJoints": [
                {
                    "fingerName": "Thumb",
                    "jointPositions": [
                        {
                            "x": -0.00650551775470376,
                            "y": 0.4324262738227844,
                            "z": -0.2036062479019165
                        },
                        {
                            "x": -0.03629915416240692,
                            "y": 0.4622974693775177,
                            "z": -0.18169330060482026
                        },
                        {
                            "x": -0.05337994918227196,
                            "y": 0.47712182998657229,
                            "z": -0.16682873666286469
                        },
                        {
                            "x": -0.06532031297683716,
                            "y": 0.48336750268936159,
                            "z": -0.15045194327831269
                        }
                    ]
                },
                {
                    "fingerName": "Index",
                    "jointPositions": [
                        {
                            "x": -0.010606011375784874,
                            "y": 0.4945412278175354,
                            "z": -0.16873782873153687
                        },
                        {
                            "x": -0.0305104348808527,
                            "y": 0.5047268271446228,
                            "z": -0.1481139063835144
                        },
                        {
                            "x": -0.04682551696896553,
                            "y": 0.4979311227798462,
                            "z": -0.13960351049900056
                        },
                        {
                            "x": -0.057206667959690097,
                            "y": 0.4884195923805237,
                            "z": -0.13703884184360505
                        }
                    ]
                },
                {
                    "fingerName": "Middle",
                    "jointPositions": [
                        {
                            "x": -0.0008690187241882086,
                            "y": 0.48821622133255007,
                            "z": -0.15571460127830506
                        },
                        {
                            "x": -0.02648867294192314,
                            "y": 0.500633716583252,
                            "z": -0.13414159417152406
                        },
                        {
                            "x": -0.04804592207074165,
                            "y": 0.49385589361190798,
                            "z": -0.1277836263179779
                        },
                        {
                            "x": -0.059845369309186938,
                            "y": 0.4837011694908142,
                            "z": -0.1290842443704605
                        }
                    ]
                },
                {
                    "fingerName": "Ring",
                    "jointPositions": [
                        {
                            "x": 0.007132649887353182,
                            "y": 0.4740530550479889,
                            "z": -0.14282648265361787
                        },
                        {
                            "x": -0.014831860549747944,
                            "y": 0.4864007234573364,
                            "z": -0.12050971388816834
                        },
                        {
                            "x": -0.0326051339507103,
                            "y": 0.48386746644973757,
                            "z": -0.11458795517683029
                        },
                        {
                            "x": -0.046978555619716647,
                            "y": 0.4765266478061676,
                            "z": -0.11459517478942871
                        }
                    ]
                },
                {
                    "fingerName": "Pinky",
                    "jointPositions": [
                        {
                            "x": 0.010872896760702134,
                            "y": 0.4573918282985687,
                            "z": -0.1353898048400879
                        },
                        {
                            "x": -0.0030463796574622394,
                            "y": 0.46762600541114809,
                            "z": -0.11778200417757034
                        },
                        {
                            "x": -0.01996489241719246,
                            "y": 0.46745383739471438,
                            "z": -0.11168612539768219
                        },
                        {
                            "x": -0.03172609582543373,
                            "y": 0.4625290334224701,
                            "z": -0.11336106806993485
                        }
                    ]
                }
            ],
            "poseName": "zero"
        },
        {
            "handID": "R",
            "handPosition": {
                "x": 0.007720923982560635,
                "y": 0.4199123978614807,
                "z": -0.21494445204734803
            },
            "handRotation": {
                "x": -0.18449614942073823,
                "y": -0.7005489468574524,
                "z": 0.30740970373153689,
                "w": 0.6170022487640381
            },
            "handOrientation": "Front",
            "fingerJoints": [
                {
                    "fingerName": "Thumb",
                    "jointPositions": [
                        {
                            "x": -0.016751473769545556,
                            "y": 0.4193805456161499,
                            "z": -0.19548818469047547
                        },
                        {
                            "x": -0.037989452481269839,
                            "y": 0.43952643871307375,
                            "z": -0.1617995947599411
                        },
                        {
                            "x": -0.04166035354137421,
                            "y": 0.45054319500923159,
                            "z": -0.13954538106918336
                        },
                        {
                            "x": -0.03250613808631897,
                            "y": 0.4563632607460022,
                            "z": -0.12240825593471527
                        }
                    ]
                },
                {
                    "fingerName": "Index",
                    "jointPositions": [
                        {
                            "x": -0.03379834070801735,
                            "y": 0.4645180106163025,
                            "z": -0.14633508026599885
                        },
                        {
                            "x": -0.041840143501758578,
                            "y": 0.4853510856628418,
                            "z": -0.12787429988384248
                        },
                        {
                            "x": -0.047317858785390857,
                            "y": 0.49983513355255129,
                            "z": -0.1142648234963417
                        },
                        {
                            "x": -0.05146775767207146,
                            "y": 0.5101940631866455,
                            "z": -0.10373412817716599
                        }
                    ]
                },
                {
                    "fingerName": "Middle",
                    "jointPositions": [
                        {
                            "x": -0.01692713052034378,
                            "y": 0.4703816771507263,
                            "z": -0.14636506140232087
                        },
                        {
                            "x": -0.01898796483874321,
                            "y": 0.4581558108329773,
                            "z": -0.11424034088850022
                        },
                        {
                            "x": -0.016681000590324403,
                            "y": 0.43572843074798586,
                            "z": -0.11836143583059311
                        },
                        {
                            "x": -0.014777421951293946,
                            "y": 0.4265236258506775,
                            "z": -0.13311336934566499
                        }
                    ]
                },
                {
                    "fingerName": "Ring",
                    "jointPositions": [
                        {
                            "x": 0.003615405410528183,
                            "y": 0.4700910151004791,
                            "z": -0.14851047098636628
                        },
                        {
                            "x": 0.0018951150123029948,
                            "y": 0.4587971866130829,
                            "z": -0.11924872547388077
                        },
                        {
                            "x": 0.0007765963091515005,
                            "y": 0.4421249330043793,
                            "z": -0.12254554778337479
                        },
                        {
                            "x": 0.0005393209285102785,
                            "y": 0.4321189522743225,
                            "z": -0.13622254133224488
                        }
                    ]
                },
                {
                    "fingerName": "Pinky",
                    "jointPositions": [
                        {
                            "x": 0.02036477066576481,
                            "y": 0.46415212750434878,
                            "z": -0.1524195522069931
                        },
                        {
                            "x": 0.014547440223395825,
                            "y": 0.45329850912094118,
                            "z": -0.13346703350543977
                        },
                        {
                            "x": 0.010235626250505448,
                            "y": 0.4369334876537323,
                            "z": -0.13701283931732179
                        },
                        {
                            "x": 0.0094109196215868,
                            "y": 0.4307261109352112,
                            "z": -0.14937704801559449
                        }
                    ]
                }
            ],
            "poseName": "one"
        },
        {
            "handID": "R",
            "handPosition": {
                "x": 0.009423081763088704,
                "y": 0.41623610258102419,
                "z": -0.21061494946479798
            },
            "handRotation": {
                "x": -0.17630168795585633,
                "y": -0.7270117998123169,
                "z": 0.32753440737724306,
                "w": 0.5771421194076538
            },
            "handOrientation": "Front",
            "fingerJoints": [
                {
                    "fingerName": "Thumb",
                    "jointPositions": [
                        {
                            "x": -0.014880774542689324,
                            "y": 0.41436833143234255,
                            "z": -0.19315457344055177
                        },
                        {
                            "x": -0.03104066103696823,
                            "y": 0.4337071180343628,
                            "z": -0.16079938411712647
                        },
                        {
                            "x": -0.030346719548106195,
                            "y": 0.4446638524532318,
                            "z": -0.13988667726516725
                        },
                        {
                            "x": -0.019425619393587114,
                            "y": 0.45066720247268679,
                            "z": -0.1253378838300705
                        }
                    ]
                },
                {
                    "fingerName": "Index",
                    "jointPositions": [
                        {
                            "x": -0.0383785106241703,
                            "y": 0.4574355185031891,
                            "z": -0.14759686589241029
                        },
                        {
                            "x": -0.05393119528889656,
                            "y": 0.47364306449890139,
                            "z": -0.13085037469863892
                        },
                        {
                            "x": -0.06389772146940232,
                            "y": 0.48268216848373415,
                            "z": -0.11817631870508194
                        },
                        {
                            "x": -0.07124015688896179,
                            "y": 0.4888926148414612,
                            "z": -0.10774745047092438
                        }
                    ]
                },
                {
                    "fingerName": "Middle",
                    "jointPositions": [
                        {
                            "x": -0.02245006337761879,
                            "y": 0.4642127752304077,
                            "z": -0.14666014909744264
                        },
                        {
                            "x": -0.020872922614216806,
                            "y": 0.48733705282211306,
                            "z": -0.12315667420625687
                        },
                        {
                            "x": -0.01738029718399048,
                            "y": 0.5023666620254517,
                            "z": -0.10513809323310852
                        },
                        {
                            "x": -0.01522600743919611,
                            "y": 0.5116488337516785,
                            "z": -0.09070347249507904
                        }
                    ]
                },
                {
                    "fingerName": "Ring",
                    "jointPositions": [
                        {
                            "x": -0.002393231261521578,
                            "y": 0.4653446674346924,
                            "z": -0.1471668928861618
                        },
                        {
                            "x": -0.005624493584036827,
                            "y": 0.46212849020957949,
                            "z": -0.11597773432731629
                        },
                        {
                            "x": -0.006607720162719488,
                            "y": 0.446577250957489,
                            "z": -0.11251452565193176
                        },
                        {
                            "x": -0.006180623546242714,
                            "y": 0.4323198199272156,
                            "z": -0.1208670437335968
                        }
                    ]
                },
                {
                    "fingerName": "Pinky",
                    "jointPositions": [
                        {
                            "x": 0.014635708183050156,
                            "y": 0.46068549156188967,
                            "z": -0.149497851729393
                        },
                        {
                            "x": 0.00816765520721674,
                            "y": 0.4486759901046753,
                            "z": -0.13206587731838227
                        },
                        {
                            "x": 0.005293022375553846,
                            "y": 0.43135643005371096,
                            "z": -0.13499918580055238
                        },
                        {
                            "x": 0.005527809262275696,
                            "y": 0.423849880695343,
                            "z": -0.1469832807779312
                        }
                    ]
                }
            ],
            "poseName": "two"
        },
        {
            "handID": "R",
            "handPosition": {
                "x": 0.010678865946829319,
                "y": 0.4102778732776642,
                "z": -0.2184571474790573
            },
            "handRotation": {
                "x": 0.23654575645923615,
                "y": 0.7386922240257263,
                "z": -0.29986414313316347,
                "w": -0.5553931593894959
            },
            "handOrientation": "Front",
            "fingerJoints": [
                {
                    "fingerName": "Thumb",
                    "jointPositions": [
                        {
                            "x": -0.0155134042724967,
                            "y": 0.41077685356140139,
                            "z": -0.20295074582099915
                        },
                        {
                            "x": -0.05626898631453514,
                            "y": 0.4165549874305725,
                            "z": -0.18271756172180177
                        },
                        {
                            "x": -0.07859233766794205,
                            "y": 0.4207664132118225,
                            "z": -0.1706041544675827
                        },
                        {
                            "x": -0.09244300425052643,
                            "y": 0.4255673885345459,
                            "z": -0.15704548358917237
                        }
                    ]
                },
                {
                    "fingerName": "Index",
                    "jointPositions": [
                        {
                            "x": -0.03884672001004219,
                            "y": 0.45857250690460207,
                            "z": -0.160017192363739
                        },
                        {
                            "x": -0.054723892360925677,
                            "y": 0.4749375879764557,
                            "z": -0.1452275663614273
                        },
                        {
                            "x": -0.06520470976829529,
                            "y": 0.4843078851699829,
                            "z": -0.1344204843044281
                        },
                        {
                            "x": -0.07325673848390579,
                            "y": 0.490933358669281,
                            "z": -0.12519147992134095
                        }
                    ]
                },
                {
                    "fingerName": "Middle",
                    "jointPositions": [
                        {
                            "x": -0.022038431838154794,
                            "y": 0.46431416273117068,
                            "z": -0.1575237214565277
                        },
                        {
                            "x": -0.021483641117811204,
                            "y": 0.4873468279838562,
                            "z": -0.13381990790367127
                        },
                        {
                            "x": -0.01906256191432476,
                            "y": 0.5021516680717468,
                            "z": -0.11525629460811615
                        },
                        {
                            "x": -0.018011653795838357,
                            "y": 0.5112209916114807,
                            "z": -0.10007233172655106
                        }
                    ]
                },
                {
                    "fingerName": "Ring",
                    "jointPositions": [
                        {
                            "x": -0.0014743836363777519,
                            "y": 0.46349090337753298,
                            "z": -0.15586979687213899
                        },
                        {
                            "x": -0.008546994999051094,
                            "y": 0.4592745900154114,
                            "z": -0.12598571181297303
                        },
                        {
                            "x": -0.01049016322940588,
                            "y": 0.4432086944580078,
                            "z": -0.12373992055654526
                        },
                        {
                            "x": -0.009346893057227135,
                            "y": 0.42927369475364687,
                            "z": -0.13243384659290315
                        }
                    ]
                },
                {
                    "fingerName": "Pinky",
                    "jointPositions": [
                        {
                            "x": 0.01537932176142931,
                            "y": 0.45683372020721438,
                            "z": -0.15638971328735352
                        },
                        {
                            "x": 0.0073054488748312,
                            "y": 0.446368932723999,
                            "z": -0.13764098286628724
                        },
                        {
                            "x": 0.0031222510151565077,
                            "y": 0.4283115267753601,
                            "z": -0.1390448361635208
                        },
                        {
                            "x": 0.0034785764291882517,
                            "y": 0.4193287491798401,
                            "z": -0.15068626403808595
                        }
                    ]
                }
            ],
            "poseName": "three"
        },
        {
            "handID": "R",
            "handPosition": {
                "x": 0.010578206740319729,
                "y": 0.4030960202217102,
                "z": -0.20847418904304505
            },
            "handRotation": {
                "x": -0.20801100134849549,
                "y": -0.7657939195632935,
                "z": 0.32671642303466799,
                "w": 0.5133689641952515
            },
            "handOrientation": "Front",
            "fingerJoints": [
                {
                    "fingerName": "Thumb",
                    "jointPositions": [
                        {
                            "x": -0.01645854115486145,
                            "y": 0.401508092880249,
                            "z": -0.19477427005767823
                        },
                        {
                            "x": -0.03955015540122986,
                            "y": 0.4281875491142273,
                            "z": -0.1696406453847885
                        },
                        {
                            "x": -0.046822432428598407,
                            "y": 0.44382163882255556,
                            "z": -0.15236219763755799
                        },
                        {
                            "x": -0.04532908275723457,
                            "y": 0.45482105016708376,
                            "z": -0.13761694729328156
                        }
                    ]
                },
                {
                    "fingerName": "Index",
                    "jointPositions": [
                        {
                            "x": -0.047853972762823108,
                            "y": 0.447007954120636,
                            "z": -0.1537008285522461
                        },
                        {
                            "x": -0.06523045897483826,
                            "y": 0.46362408995628359,
                            "z": -0.13913042843341828
                        },
                        {
                            "x": -0.07680575549602509,
                            "y": 0.47482797503471377,
                            "z": -0.1292855143547058
                        },
                        {
                            "x": -0.08565228432416916,
                            "y": 0.48306888341903689,
                            "z": -0.12114408612251282
                        }
                    ]
                },
                {
                    "fingerName": "Middle",
                    "jointPositions": [
                        {
                            "x": -0.03174451366066933,
                            "y": 0.45464062690734866,
                            "z": -0.14998093247413636
                        },
                        {
                            "x": -0.03998926281929016,
                            "y": 0.4792099595069885,
                            "z": -0.12860579788684846
                        },
                        {
                            "x": -0.04538450762629509,
                            "y": 0.49792569875717165,
                            "z": -0.114185631275177
                        },
                        {
                            "x": -0.04902941733598709,
                            "y": 0.5117020606994629,
                            "z": -0.10288611054420471
                        }
                    ]
                },
                {
                    "fingerName": "Ring",
                    "jointPositions": [
                        {
                            "x": -0.010998680256307125,
                            "y": 0.4563230872154236,
                            "z": -0.14692771434783936
                        },
                        {
                            "x": -0.010921494103968144,
                            "y": 0.47993236780166628,
                            "z": -0.12390806525945664
                        },
                        {
                            "x": -0.010841373354196549,
                            "y": 0.4927912950515747,
                            "z": -0.10976823419332504
                        },
                        {
                            "x": -0.011180439963936806,
                            "y": 0.5038790106773377,
                            "z": -0.09608606994152069
                        }
                    ]
                },
                {
                    "fingerName": "Pinky",
                    "jointPositions": [
                        {
                            "x": 0.007005270570516586,
                            "y": 0.45190513134002688,
                            "z": -0.14619489014148713
                        },
                        {
                            "x": 0.013802013359963894,
                            "y": 0.4675683081150055,
                            "z": -0.12986034154891969
                        },
                        {
                            "x": 0.018404554575681688,
                            "y": 0.47776296734809878,
                            "z": -0.11584506928920746
                        },
                        {
                            "x": 0.02142581343650818,
                            "y": 0.4849395751953125,
                            "z": -0.10442433506250382
                        }
                    ]
                }
            ],
            "poseName": "four"
        },
        {
            "handID": "R",
            "handPosition": {
                "x": 0.0215448085218668,
                "y": 0.4010865092277527,
                "z": -0.21029877662658692
            },
            "handRotation": {
                "x": -0.2677009701728821,
                "y": -0.7420021295547485,
                "z": 0.28423401713371279,
                "w": 0.5449588298797607
            },
            "handOrientation": "Front",
            "fingerJoints": [
                {
                    "fingerName": "Thumb",
                    "jointPositions": [
                        {
                            "x": -0.006641348358243704,
                            "y": 0.4014859199523926,
                            "z": -0.19474945962429048
                        },
                        {
                            "x": -0.04978165403008461,
                            "y": 0.4108537435531616,
                            "z": -0.17870555818080903
                        },
                        {
                            "x": -0.07294511049985886,
                            "y": 0.41736072301864626,
                            "z": -0.16779816150665284
                        },
                        {
                            "x": -0.08834725618362427,
                            "y": 0.42342132329940798,
                            "z": -0.15544459223747254
                        }
                    ]
                },
                {
                    "fingerName": "Index",
                    "jointPositions": [
                        {
                            "x": -0.030266892164945604,
                            "y": 0.45334726572036745,
                            "z": -0.1519218534231186
                        },
                        {
                            "x": -0.04711955785751343,
                            "y": 0.47143322229385378,
                            "z": -0.13887307047843934
                        },
                        {
                            "x": -0.05835749953985214,
                            "y": 0.48326605558395388,
                            "z": -0.12965533137321473
                        },
                        {
                            "x": -0.06691932678222656,
                            "y": 0.49178093671798708,
                            "z": -0.12176714092493057
                        }
                    ]
                },
                {
                    "fingerName": "Middle",
                    "jointPositions": [
                        {
                            "x": -0.012479319237172604,
                            "y": 0.45839452743530276,
                            "z": -0.14847122132778169
                        },
                        {
                            "x": -0.01599019020795822,
                            "y": 0.4857889413833618,
                            "z": -0.13086718320846559
                        },
                        {
                            "x": -0.017812032252550126,
                            "y": 0.5057491064071655,
                            "z": -0.11778520792722702
                        },
                        {
                            "x": -0.01929350756108761,
                            "y": 0.5200300812721252,
                            "z": -0.10727433115243912
                        }
                    ]
                },
                {
                    "fingerName": "Ring",
                    "jointPositions": [
                        {
                            "x": 0.009017791599035263,
                            "y": 0.45636552572250368,
                            "z": -0.1457495391368866
                        },
                        {
                            "x": 0.009335018694400788,
                            "y": 0.48307114839553835,
                            "z": -0.12642653286457063
                        },
                        {
                            "x": 0.008809506893157959,
                            "y": 0.4971000552177429,
                            "z": -0.11347497254610062
                        },
                        {
                            "x": 0.007804778404533863,
                            "y": 0.5090124011039734,
                            "z": -0.10104174166917801
                        }
                    ]
                },
                {
                    "fingerName": "Pinky",
                    "jointPositions": [
                        {
                            "x": 0.026410864666104318,
                            "y": 0.44854873418807986,
                            "z": -0.14534056186676026
                        },
                        {
                            "x": 0.03717970475554466,
                            "y": 0.4632686972618103,
                            "z": -0.12891623377799989
                        },
                        {
                            "x": 0.043424706906080249,
                            "y": 0.4727996587753296,
                            "z": -0.1135440245270729
                        },
                        {
                            "x": 0.0470808781683445,
                            "y": 0.4790794849395752,
                            "z": -0.10112056136131287
                        }
                    ]
                }
            ],
            "poseName": "five"
        },
        {
            "handID": "R",
            "handPosition": {
                "x": 0.017261335626244546,
                "y": 0.39132004976272585,
                "z": -0.20394733548164369
            },
            "handRotation": {
                "x": -0.1939467042684555,
                "y": -0.8011175394058228,
                "z": 0.292530357837677,
                "w": 0.484790176153183
            },
            "handOrientation": "Front",
            "fingerJoints": [
                {
                    "fingerName": "Thumb",
                    "jointPositions": [
                        {
                            "x": -0.010816558264195919,
                            "y": 0.3887549042701721,
                            "z": -0.19213895499706269
                        },
                        {
                            "x": -0.030176281929016115,
                            "y": 0.4098994731903076,
                            "z": -0.15848541259765626
                        },
                        {
                            "x": -0.0313616506755352,
                            "y": 0.42132827639579775,
                            "z": -0.13580094277858735
                        },
                        {
                            "x": -0.02190428040921688,
                            "y": 0.4279499351978302,
                            "z": -0.11889991164207459
                        }
                    ]
                },
                {
                    "fingerName": "Index",
                    "jointPositions": [
                        {
                            "x": -0.04758695513010025,
                            "y": 0.4315948188304901,
                            "z": -0.14932242035865785
                        },
                        {
                            "x": -0.06846409291028977,
                            "y": 0.4411594271659851,
                            "z": -0.12952032685279847
                        },
                        {
                            "x": -0.08249589800834656,
                            "y": 0.4456373453140259,
                            "z": -0.11481361091136933
                        },
                        {
                            "x": -0.09333435446023941,
                            "y": 0.44794777035713198,
                            "z": -0.10288113355636597
                        }
                    ]
                },
                {
                    "fingerName": "Middle",
                    "jointPositions": [
                        {
                            "x": -0.03158150985836983,
                            "y": 0.43928346037864687,
                            "z": -0.14388442039489747
                        },
                        {
                            "x": -0.040350962430238727,
                            "y": 0.46649402379989626,
                            "z": -0.12430082261562348
                        },
                        {
                            "x": -0.047141123563051227,
                            "y": 0.4857838749885559,
                            "z": -0.11024876683950424
                        },
                        {
                            "x": -0.05225306749343872,
                            "y": 0.49926120042800906,
                            "z": -0.09855470806360245
                        }
                    ]
                },
                {
                    "fingerName": "Ring",
                    "jointPositions": [
                        {
                            "x": -0.010800697840750218,
                            "y": 0.44096291065216067,
                            "z": -0.13885632157325746
                        },
                        {
                            "x": -0.01151602528989315,
                            "y": 0.46230843663215639,
                            "z": -0.1106126680970192
                        },
                        {
                            "x": -0.012059335596859455,
                            "y": 0.47281086444854739,
                            "z": -0.09308919310569763
                        },
                        {
                            "x": -0.013026950880885125,
                            "y": 0.48059797286987307,
                            "z": -0.0756724625825882
                        }
                    ]
                },
                {
                    "fingerName": "Pinky",
                    "jointPositions": [
                        {
                            "x": 0.007480677217245102,
                            "y": 0.4365774691104889,
                            "z": -0.1368405669927597
                        },
                        {
                            "x": -0.0014326670207083226,
                            "y": 0.44607293605804446,
                            "z": -0.11838168650865555
                        },
                        {
                            "x": -0.009557107463479042,
                            "y": 0.44573113322257998,
                            "z": -0.10539115965366364
                        },
                        {
                            "x": -0.01594877615571022,
                            "y": 0.44091105461120608,
                            "z": -0.09699586778879166
                        }
                    ]
                }
            ],
            "poseName": "six"
        },
        {
            "handID": "R",
            "handPosition": {
                "x": 0.021788649260997773,
                "y": 0.39142906665802,
                "z": -0.20300014317035676
            },
            "handRotation": {
                "x": 0.1930711269378662,
                "y": 0.7635881304740906,
                "z": -0.2917673885822296,
                "w": -0.5427049994468689
            },
            "handOrientation": "Front",
            "fingerJoints": [
                {
                    "fingerName": "Thumb",
                    "jointPositions": [
                        {
                            "x": -0.005396364256739616,
                            "y": 0.3890700936317444,
                            "z": -0.18790873885154725
                        },
                        {
                            "x": -0.026193998754024507,
                            "y": 0.40621063113212588,
                            "z": -0.15298892557621003
                        },
                        {
                            "x": -0.02785046398639679,
                            "y": 0.4153599739074707,
                            "z": -0.12990668416023255
                        },
                        {
                            "x": -0.01825140044093132,
                            "y": 0.42002373933792117,
                            "z": -0.11372724920511246
                        }
                    ]
                },
                {
                    "fingerName": "Index",
                    "jointPositions": [
                        {
                            "x": -0.033748142421245578,
                            "y": 0.43266600370407107,
                            "z": -0.1418500393629074
                        },
                        {
                            "x": -0.05552518367767334,
                            "y": 0.4449473023414612,
                            "z": -0.1254570335149765
                        },
                        {
                            "x": -0.06908083707094193,
                            "y": 0.45006263256073,
                            "z": -0.11271172761917114
                        },
                        {
                            "x": -0.07883352041244507,
                            "y": 0.4523699879646301,
                            "z": -0.1020827665925026
                        }
                    ]
                },
                {
                    "fingerName": "Middle",
                    "jointPositions": [
                        {
                            "x": -0.017123203724622728,
                            "y": 0.4393218159675598,
                            "z": -0.13839487731456757
                        },
                        {
                            "x": -0.025783898308873178,
                            "y": 0.4650096893310547,
                            "z": -0.11980545520782471
                        },
                        {
                            "x": -0.031190579757094384,
                            "y": 0.4814724922180176,
                            "z": -0.10421085357666016
                        },
                        {
                            "x": -0.03499099612236023,
                            "y": 0.49089300632476809,
                            "z": -0.09056935459375382
                        }
                    ]
                },
                {
                    "fingerName": "Ring",
                    "jointPositions": [
                        {
                            "x": 0.0039871931076049809,
                            "y": 0.4400481581687927,
                            "z": -0.1361287385225296
                        },
                        {
                            "x": -0.0037170620635151865,
                            "y": 0.43705305457115176,
                            "z": -0.10774270445108414
                        },
                        {
                            "x": -0.004912019241601229,
                            "y": 0.4232109785079956,
                            "z": -0.10208790004253388
                        },
                        {
                            "x": -0.0038784509524703027,
                            "y": 0.4075442850589752,
                            "z": -0.10529640316963196
                        }
                    ]
                },
                {
                    "fingerName": "Pinky",
                    "jointPositions": [
                        {
                            "x": 0.021963059902191163,
                            "y": 0.43491581082344057,
                            "z": -0.1364862322807312
                        },
                        {
                            "x": 0.031802598387002948,
                            "y": 0.4489102363586426,
                            "z": -0.11883408576250076
                        },
                        {
                            "x": 0.037102553993463519,
                            "y": 0.4558103084564209,
                            "z": -0.10060510039329529
                        },
                        {
                            "x": 0.03907278552651405,
                            "y": 0.4578806757926941,
                            "z": -0.08784716576337815
                        }
                    ]
                }
            ],
            "poseName": "seven"
        },
        {
            "handID": "R",
            "handPosition": {
                "x": 0.030802082270383836,
                "y": 0.4420793652534485,
                "z": -0.20499853789806367
            },
            "handRotation": {
                "x": -0.3316042423248291,
                "y": -0.6749270558357239,
                "z": 0.3439056873321533,
                "w": 0.5623531341552734
            },
            "handOrientation": "Front",
            "fingerJoints": [
                {
                    "fingerName": "Thumb",
                    "jointPositions": [
                        {
                            "x": 0.001948994118720293,
                            "y": 0.44683587551116946,
                            "z": -0.18744492530822755
                        },
                        {
                            "x": -0.02455831505358219,
                            "y": 0.47501808404922488,
                            "z": -0.160932257771492
                        },
                        {
                            "x": -0.032579705119132999,
                            "y": 0.49084168672561648,
                            "z": -0.141152024269104
                        },
                        {
                            "x": -0.029090188443660737,
                            "y": 0.5015780329704285,
                            "z": -0.1234498992562294
                        }
                    ]
                },
                {
                    "fingerName": "Index",
                    "jointPositions": [
                        {
                            "x": -0.013486073352396489,
                            "y": 0.5088292956352234,
                            "z": -0.15226982533931733
                        },
                        {
                            "x": -0.026899119839072229,
                            "y": 0.5268995761871338,
                            "z": -0.13833411037921906
                        },
                        {
                            "x": -0.03644315525889397,
                            "y": 0.5340625047683716,
                            "z": -0.13006280362606049
                        },
                        {
                            "x": -0.04500904306769371,
                            "y": 0.5388998985290527,
                            "z": -0.12407159805297852
                        }
                    ]
                },
                {
                    "fingerName": "Middle",
                    "jointPositions": [
                        {
                            "x": 0.004413597285747528,
                            "y": 0.5127825736999512,
                            "z": -0.15122391283512116
                        },
                        {
                            "x": -0.006858464330434799,
                            "y": 0.5122788548469544,
                            "z": -0.1207006648182869
                        },
                        {
                            "x": -0.008284351788461209,
                            "y": 0.49255651235580447,
                            "z": -0.11151902377605438
                        },
                        {
                            "x": -0.005221692379564047,
                            "y": 0.47647520899772646,
                            "z": -0.114901103079319
                        }
                    ]
                },
                {
                    "fingerName": "Ring",
                    "jointPositions": [
                        {
                            "x": 0.02577666938304901,
                            "y": 0.509454607963562,
                            "z": -0.15020544826984406
                        },
                        {
                            "x": 0.024169377982616426,
                            "y": 0.5279542803764343,
                            "z": -0.12139207869768143
                        },
                        {
                            "x": 0.022221172228455545,
                            "y": 0.5326820611953735,
                            "z": -0.1033734679222107
                        },
                        {
                            "x": 0.019902575761079789,
                            "y": 0.5344353914260864,
                            "z": -0.0862632766366005
                        }
                    ]
                },
                {
                    "fingerName": "Pinky",
                    "jointPositions": [
                        {
                            "x": 0.042631685733795169,
                            "y": 0.5003732442855835,
                            "z": -0.15008258819580079
                        },
                        {
                            "x": 0.05834636092185974,
                            "y": 0.5172027349472046,
                            "z": -0.14305712282657624
                        },
                        {
                            "x": 0.07018143683671951,
                            "y": 0.5292543172836304,
                            "z": -0.13623589277267457
                        },
                        {
                            "x": 0.07833558320999146,
                            "y": 0.5387372374534607,
                            "z": -0.12974770367145539
                        }
                    ]
                }
            ],
            "poseName": "eight"
        },
        {
            "handID": "R",
            "handPosition": {
                "x": 0.027164382860064508,
                "y": 0.4326753616333008,
                "z": -0.20168443024158479
            },
            "handRotation": {
                "x": -0.29634323716163638,
                "y": -0.7395170331001282,
                "z": 0.28560298681259158,
                "w": 0.532659649848938
            },
            "handOrientation": "Front",
            "fingerJoints": [
                {
                    "fingerName": "Thumb",
                    "jointPositions": [
                        {
                            "x": -0.0014721467159688473,
                            "y": 0.43572184443473818,
                            "z": -0.1882283240556717
                        },
                        {
                            "x": -0.03646712005138397,
                            "y": 0.4552994966506958,
                            "z": -0.16513513028621674
                        },
                        {
                            "x": -0.051413148641586307,
                            "y": 0.4668653905391693,
                            "z": -0.14724867045879365
                        },
                        {
                            "x": -0.052882157266139987,
                            "y": 0.4742327034473419,
                            "z": -0.12835538387298585
                        }
                    ]
                },
                {
                    "fingerName": "Index",
                    "jointPositions": [
                        {
                            "x": -0.023676034063100816,
                            "y": 0.48947960138320925,
                            "z": -0.1484251171350479
                        },
                        {
                            "x": -0.03772050887346268,
                            "y": 0.4843936562538147,
                            "z": -0.1255132406949997
                        },
                        {
                            "x": -0.03880773484706879,
                            "y": 0.4670102596282959,
                            "z": -0.11834738403558731
                        },
                        {
                            "x": -0.036239851266145709,
                            "y": 0.45304614305496218,
                            "z": -0.11808835715055466
                        }
                    ]
                },
                {
                    "fingerName": "Middle",
                    "jointPositions": [
                        {
                            "x": -0.006563915405422449,
                            "y": 0.4939368963241577,
                            "z": -0.14479181170463563
                        },
                        {
                            "x": -0.015099969692528248,
                            "y": 0.5155234932899475,
                            "z": -0.12226320803165436
                        },
                        {
                            "x": -0.02065357379615307,
                            "y": 0.5304723381996155,
                            "z": -0.10589475929737091
                        },
                        {
                            "x": -0.024937499314546586,
                            "y": 0.5405096411705017,
                            "z": -0.0925484225153923
                        }
                    ]
                },
                {
                    "fingerName": "Ring",
                    "jointPositions": [
                        {
                            "x": 0.013944496400654316,
                            "y": 0.49137330055236819,
                            "z": -0.14142335951328278
                        },
                        {
                            "x": 0.012999017722904683,
                            "y": 0.5152141451835632,
                            "z": -0.11939334124326706
                        },
                        {
                            "x": 0.011748012155294419,
                            "y": 0.5271102786064148,
                            "z": -0.10574397444725037
                        },
                        {
                            "x": 0.010194370523095131,
                            "y": 0.5376178026199341,
                            "z": -0.09304434806108475
                        }
                    ]
                },
                {
                    "fingerName": "Pinky",
                    "jointPositions": [
                        {
                            "x": 0.030509818345308305,
                            "y": 0.4832586646080017,
                            "z": -0.14013820886611939
                        },
                        {
                            "x": 0.040707219392061236,
                            "y": 0.49874669313430788,
                            "z": -0.12460292130708695
                        },
                        {
                            "x": 0.047284454107284549,
                            "y": 0.509333074092865,
                            "z": -0.11054633557796478
                        },
                        {
                            "x": 0.05157894268631935,
                            "y": 0.516825795173645,
                            "z": -0.09954916685819626
                        }
                    ]
                }
            ],
            "poseName": "nine"
        }
    ]
}